LICENSE
MANIFEST.in
setup.py
tidytree/__init__.py
tidytree/cli.py
tidytree.egg-info/PKG-INFO
tidytree.egg-info/SOURCES.txt
tidytree.egg-info/dependency_links.txt
tidytree.egg-info/entry_points.txt
tidytree.egg-info/requires.txt
tidytree.egg-info/top_level.txt