Metadata-Version: 1.1
Name: tidytree
Version: 0.1.1
Summary: manager directories
Home-page: https://github.com/tsalmon/tidytree
Author: Salmon Thomas
Author-email: ths871@gmail.com
License: The MIT License (MIT)
